odoo/addons/sale_quotation/README.rst
odoo/addons/sale_quotation/__init__.py
odoo/addons/sale_quotation/__manifest__.py
odoo/addons/sale_quotation/i18n/sale_quotation.pot
odoo/addons/sale_quotation/models/__init__.py
odoo/addons/sale_quotation/models/product_product.py
odoo/addons/sale_quotation/models/product_template.py
odoo/addons/sale_quotation/models/sale_order.py
odoo/addons/sale_quotation/readme/CONTRIBUTORS.rst
odoo/addons/sale_quotation/readme/DESCRIPTION.rst
odoo/addons/sale_quotation/static/description/index.html
odoo/addons/sale_quotation/static/description/product.png
odoo/addons/sale_quotation/static/description/quotation.png
odoo/addons/sale_quotation/tests/__init__.py
odoo/addons/sale_quotation/tests/test_product.py
odoo/addons/sale_quotation/tests/test_quotation.py
odoo/addons/sale_quotation/views/product_view.xml
odoo/addons/sale_quotation/views/sale_view.xml
odoo_addon_sale_quotation-16.0.0.2.0.dist-info/METADATA
odoo_addon_sale_quotation-16.0.0.2.0.dist-info/WHEEL
odoo_addon_sale_quotation-16.0.0.2.0.dist-info/top_level.txt
odoo_addon_sale_quotation-16.0.0.2.0.dist-info/RECORD
